{"cameraMode":{"drawMode":0,"name":"Shaded","section":"Shading Mode"},"sceneLighting":true,"audioPlay":false,"sceneViewState":{"showFog":true,"showMaterialUpdate":false,"showSkybox":true,"showFlares":true,"showImageEffects":true,"showParticleSystems":true},"in2DMode":false,"pivot":{"x":-25.098148345947267,"y":3.364121913909912,"z":-23.918453216552736},"rotation":{"x":-0.09020975232124329,"y":-0.9073383808135986,"z":0.323316752910614,"w":-0.2531437873840332},"size":26.52260971069336,"orthographic":false}